eip712/__init__.py
eip712/common.py
eip712/messages.py
eip712/py.typed
eip712/utils.py
eip712/version.py
eip712-0.3.0.dist-info/licenses/LICENSE
eip712-0.3.0.dist-info/METADATA
eip712-0.3.0.dist-info/WHEEL
eip712-0.3.0.dist-info/top_level.txt
eip712-0.3.0.dist-info/RECORD
