Metadata-Version: 2.4
Name: eip712
Version: 0.3.0
Summary: eip712: Message classes for typed structured data hashing and signing in Ethereum
Author-email: "ApeWorX Ltd." <admin@apeworx.io>
License-Expression: Apache-2.0
Project-URL: Homepage, https://github.com/ApeWorX/eip712
Classifier: Development Status :: 5 - Production/Stable
Classifier: Intended Audience :: Developers
Classifier: Natural Language :: English
Classifier: Operating System :: MacOS
Classifier: Operating System :: POSIX
Classifier: Operating System :: Microsoft :: Windows
Classifier: Programming Language :: Python :: 3
Classifier: Programming Language :: Python :: 3.10
Classifier: Programming Language :: Python :: 3.11
Classifier: Programming Language :: Python :: 3.12
Classifier: Programming Language :: Python :: 3.13
Classifier: Programming Language :: Python :: 3.14
Requires-Python: <4,>=3.10
License-File: LICENSE
Requires-Dist: pydantic<3,>=2
Requires-Dist: eth-account<0.14,>=0.11.3
Requires-Dist: eth-pydantic-types<0.3,>=0.2.4
Requires-Dist: eth-utils<6,>=2.3.1
Dynamic: license-file
